src/register.v
/* register.v : a register in the register file */

module register
#(parameter BITS = 16)
(
	input  CLK, 		/* CLK 	 */
	input  RSTb,		/* Reset */
	input  [BITS - 1 : 0] inALU,    /* input to register from ALU */
	input  LDb_ALU, 			    /* load register from ALU     */

	input  [BITS - 1 : 0] inM,	    /* input from memory 		 */
	input  LDb_M,				    /* load register from memory  */

	input  [BITS - 1 : 0] inP,		/* input from pipeline */
	input  LDb_P,

	output [BITS - 1 : 0] outA,     /* output to ALU A    	 */
	input  OEb_A, 				    /* output enable         */

	output [BITS - 1 : 0] outB,     /* output to ALU B    	 */
	input  OEb_B, 				    /* output enable         */

	output [BITS - 1 : 0] outM,     /* output to Memory   	 */
	input  OEb_M, 					/* output enable         */

	output [BITS - 1 : 0] outMADDR, /* output to Memory Address */
	input  OEb_MADDR, 				/* output enable         */
	input  INCb						/* increment 			 */			
);

reg [BITS - 1 : 0] Reg;
reg [BITS - 1 : 0] Reg_next;

assign outA = OEb_A ? {BITS{1'bZ}} : Reg;
assign outB = OEb_B ? {BITS{1'bZ}} : Reg;
assign outM = OEb_M ? {BITS{1'bZ}} : Reg;
assign outMADDR = OEb_MADDR ? {BITS{1'bZ}} : Reg;

always @(posedge CLK)
begin
	if (RSTb == 0)
		Reg <= {BITS{1'b0}};
	else
		Reg <= Reg_next;
end

always @(*)
begin
	Reg_next = Reg;

	if (LDb_ALU == 0) 
		Reg_next = inALU;
	else if (LDb_M == 0)
		Reg_next = inM;
	else if (LDb_P == 0)
		Reg_next = inP;
	else if (INCb == 0)
		Reg_next = Reg + 1;
end

endmodule

src/register_file.v
/* register_file.v : a register file */

module register_file
#(parameter REG_BITS = 3 /* default 2**3 = 8 registers */, parameter BITS = 16 /* default 16 bits */)
(
	input CLK,
	input RSTb,
	input [BITS - 1 : 0] 		inALU,
	input [2**REG_BITS - 1 : 0] LD_reg_ALUb, /* Active low bit vector to load
												register(s) from ALU output */
	input [BITS - 1 : 0] 		inM, 
	input [2**REG_BITS - 1 : 0] LD_reg_Mb,  /* Active low bit vector to load
												register(s) from memory */
	input [BITS - 1 : 0] 		inP, 
	input [2**REG_BITS - 1 : 0] LD_reg_Pb,  /* Active low bit vector to load
												register(s) from pipeline (constants in instruction words etc) */

	input [REG_BITS  - 1: 0] ALU_A_SEL,   		/* index of register driving ALU A bus */

	input ALU_A_0_b,						/* control line to force ALU A input to zero - move */
	input ALU_A_1_b,						/* control line to force ALU A input to all ones - decrement */

 	input [REG_BITS - 1: 0] ALU_B_SEL,   /* index of register driving ALU B
												bus */

	input M_ENb,					  /* enable register to drive memory bus */
 	input [REG_BITS - 1 : 0] M_SEL,       /* index of register driving memory
												bus */

 	input [REG_BITS - 1 : 0] MADDR_SEL,   /* index of register driving memory 
											  address bus */

	input [2**REG_BITS : 0] INCb,  	  /* active low register increment */

 	output [BITS - 1 : 0] aluA_out,
 	output [BITS - 1 : 0] aluB_out,
 	output [BITS - 1 : 0] m_out,
	output [BITS - 1 : 0] m_addr_out 
);

/* decode selectors */
wire [2**REG_BITS-1:0] ALU_A_SEL_v_b 	= {2**REG_BITS{1'b1}} ^ (1 << ALU_A_SEL);
wire [2**REG_BITS-1:0] ALU_B_SEL_v_b 	= {2**REG_BITS{1'b1}} ^ (1 << ALU_B_SEL);
wire [2**REG_BITS-1:0] M_SEL_v_b     	= {2**REG_BITS{1'b1}} ^ (1 << M_SEL);
wire [2**REG_BITS-1:0] MADDR_SEL_v_b    = {2**REG_BITS{1'b1}} ^ (1 << MADDR_SEL);

genvar j;
generate
	for (j = 0; j < 2**REG_BITS; j = j+1)
		begin: Gen_Modules
			register #(BITS) register_inst (
				CLK, 		
				RSTb,	
				inALU,    
				LD_reg_ALUb[j], 
				inM,	
				LD_reg_Mb[j],
				inP,
				LD_reg_Pb[j],
				aluA_out,
				ALU_A_SEL_v_b[j], 
				aluB_out, 
				ALU_B_SEL_v_b[j],
				m_out,
				M_SEL_v_b[j] | M_ENb, 
				m_addr_out, 
				MADDR_SEL_v_b[j], 
				INCb[j]	
			);
		end
endgenerate

endmodule

test/register_file/regfile_tb.v
`timescale 1 ns / 1 ps
module regfile_tb;

parameter REG_BITS  = 3; 	/* 8 registers */
parameter BITS 		= 16; 	/* 16 bit registers */

reg RSTb = 0;
reg CLK  = 0;

always #10 CLK <= !CLK; // ~ 50MHz

initial begin
    #100 RSTb <= 1;
end

reg [BITS - 1 : 0] 			 inALU 		 = 0;
reg [2**REG_BITS - 1 : 0] 	 LD_reg_ALUb = 8'hff;
reg [BITS - 1 : 0] 			 inM 		 = 0;
reg [2**REG_BITS - 1 : 0] 	 LD_reg_Mb   = 8'hff;
reg [BITS - 1 : 0] 			 inP 		 = 0;
reg [2**REG_BITS - 1 : 0] 	 LD_reg_Pb   = 8'hff;

reg [REG_BITS - 1 : 0] ALU_A_SEL = 0;
reg ALU_A_0_b 					 = 1;
reg ALU_A_1_b 					 = 1;
 
reg [REG_BITS - 1 : 0] ALU_B_SEL = 0;
 
reg M_ENb = 1;

reg [REG_BITS - 1 : 0] 		M_SEL 	  = 0;
reg [REG_BITS - 1 : 0] 		MADDR_SEL = 0;
reg [2**REG_BITS - 1 : 0] 	INCb 	  = 8'hff;	

wire [BITS - 1 : 0] aluA_out;
wire [BITS - 1 : 0] aluB_out;
wire [BITS - 1 : 0] m_out;
wire [BITS - 1 : 0] m_addr_out;

initial begin
    #200 inP <= 16'h3;
	LD_reg_Pb <= 8'hfe;
	#20 inP <= 16'h2;
	LD_reg_Pb <= 8'hfd;
	#20 LD_reg_Pb <= 8'hff;
	ALU_A_SEL <= 3'b000;
	ALU_B_SEL <= 3'b001;
	#20 INCb <= 8'hfe;
end

register_file
#(.REG_BITS(REG_BITS), .BITS(BITS))
regfile
(	CLK,
	RSTb,
	inALU,
	LD_reg_ALUb, 
	inM, 
	LD_reg_Mb,
	inP, 
	LD_reg_Pb,  	
	ALU_A_SEL,	
	ALU_A_0_b,	
	ALU_A_1_b,
	ALU_B_SEL,
	M_ENb,					   	
	M_SEL,
 	MADDR_SEL,   
	INCb,  	 
 	aluA_out,
 	aluB_out,
 	m_out,
	m_addr_out 
);

initial begin
    $dumpfile("regfile.vcd");
    $dumpvars(0, regfile_tb);
    # 100000 $finish;
end

endmodule

test/register_file/regfile.vcd
$date
	Sat Jul 24 15:45:12 2021
$end
$version
	Icarus Verilog
$end
$timescale
	1ps
$end
$scope module regfile_tb $end
$var wire 16 ! aluA_out [15:0] $end
$var wire 16 " aluB_out [15:0] $end
$var wire 16 # m_addr_out [15:0] $end
$var wire 16 $ m_out [15:0] $end
$var reg 1 % ALU_A_0_b $end
$var reg 1 & ALU_A_1_b $end
$var reg 3 ' ALU_A_SEL [2:0] $end
$var reg 3 ( ALU_B_SEL [2:0] $end
$var reg 1 ) CLK $end
$var reg 8 * INCb [7:0] $end
$var reg 8 + LD_reg_ALUb [7:0] $end
$var reg 8 , LD_reg_Mb [7:0] $end
$var reg 8 - LD_reg_Pb [7:0] $end
$var reg 3 . MADDR_SEL [2:0] $end
$var reg 1 / M_ENb $end
$var reg 3 0 M_SEL [2:0] $end
$var reg 1 1 RSTb $end
$var reg 16 2 inALU [15:0] $end
$var reg 16 3 inM [15:0] $end
$var reg 16 4 inP [15:0] $end
$scope module regfile $end
$var wire 1 % ALU_A_0_b $end
$var wire 1 & ALU_A_1_b $end
$var wire 3 5 ALU_A_SEL [2:0] $end
$var wire 8 6 ALU_A_SEL_v_b [7:0] $end
$var wire 3 7 ALU_B_SEL [2:0] $end
$var wire 8 8 ALU_B_SEL_v_b [7:0] $end
$var wire 1 ) CLK $end
$var wire 9 9 INCb [8:0] $end
$var wire 8 : LD_reg_ALUb [7:0] $end
$var wire 8 ; LD_reg_Mb [7:0] $end
$var wire 8 < LD_reg_Pb [7:0] $end
$var wire 3 = MADDR_SEL [2:0] $end
$var wire 8 > MADDR_SEL_v_b [7:0] $end
$var wire 1 / M_ENb $end
$var wire 3 ? M_SEL [2:0] $end
$var wire 8 @ M_SEL_v_b [7:0] $end
$var wire 1 1 RSTb $end
$var wire 16 A aluA_out [15:0] $end
$var wire 16 B aluB_out [15:0] $end
$var wire 16 C inALU [15:0] $end
$var wire 16 D inM [15:0] $end
$var wire 16 E inP [15:0] $end
$var wire 16 F m_addr_out [15:0] $end
$var wire 16 G m_out [15:0] $end
$scope begin Gen_Modules[0] $end
$scope module register_inst $end
$var wire 1 ) CLK $end
$var wire 1 H INCb $end
$var wire 1 I LDb_ALU $end
$var wire 1 J LDb_M $end
$var wire 1 K LDb_P $end
$var wire 1 L OEb_A $end
$var wire 1 M OEb_B $end
$var wire 1 N OEb_M $end
$var wire 1 O OEb_MADDR $end
$var wire 1 1 RSTb $end
$var wire 16 P inALU [15:0] $end
$var wire 16 Q inM [15:0] $end
$var wire 16 R inP [15:0] $end
$var wire 16 S outA [15:0] $end
$var wire 16 T outB [15:0] $end
$var wire 16 U outM [15:0] $end
$var wire 16 V outMADDR [15:0] $end
$var reg 16 W Reg [15:0] $end
$var reg 16 X Reg_next [15:0] $end
$upscope $end
$upscope $end
$scope begin Gen_Modules[1] $end
$scope module register_inst $end
$var wire 1 ) CLK $end
$var wire 1 Y INCb $end
$var wire 1 Z LDb_ALU $end
$var wire 1 [ LDb_M $end
$var wire 1 \ LDb_P $end
$var wire 1 ] OEb_A $end
$var wire 1 ^ OEb_B $end
$var wire 1 _ OEb_M $end
$var wire 1 ` OEb_MADDR $end
$var wire 1 1 RSTb $end
$var wire 16 a inALU [15:0] $end
$var wire 16 b inM [15:0] $end
$var wire 16 c inP [15:0] $end
$var wire 16 d outA [15:0] $end
$var wire 16 e outB [15:0] $end
$var wire 16 f outM [15:0] $end
$var wire 16 g outMADDR [15:0] $end
$var reg 16 h Reg [15:0] $end
$var reg 16 i Reg_next [15:0] $end
$upscope $end
$upscope $end
$scope begin Gen_Modules[2] $end
$scope module register_inst $end
$var wire 1 ) CLK $end
$var wire 1 j INCb $end
$var wire 1 k LDb_ALU $end
$var wire 1 l LDb_M $end
$var wire 1 m LDb_P $end
$var wire 1 n OEb_A $end
$var wire 1 o OEb_B $end
$var wire 1 p OEb_M $end
$var wire 1 q OEb_MADDR $end
$var wire 1 1 RSTb $end
$var wire 16 r inALU [15:0] $end
$var wire 16 s inM [15:0] $end
$var wire 16 t inP [15:0] $end
$var wire 16 u outA [15:0] $end
$var wire 16 v outB [15:0] $end
$var wire 16 w outM [15:0] $end
$var wire 16 x outMADDR [15:0] $end
$var reg 16 y Reg [15:0] $end
$var reg 16 z Reg_next [15:0] $end
$upscope $end
$upscope $end
$scope begin Gen_Modules[3] $end
$scope module register_inst $end
$var wire 1 ) CLK $end
$var wire 1 { INCb $end
$var wire 1 | LDb_ALU $end
$var wire 1 } LDb_M $end
$var wire 1 ~ LDb_P $end
$var wire 1 !" OEb_A $end
$var wire 1 "" OEb_B $end
$var wire 1 #" OEb_M $end
$var wire 1 $" OEb_MADDR $end
$var wire 1 1 RSTb $end
$var wire 16 %" inALU [15:0] $end
$var wire 16 &" inM [15:0] $end
$var wire 16 '" inP [15:0] $end
$var wire 16 (" outA [15:0] $end
$var wire 16 )" outB [15:0] $end
$var wire 16 *" outM [15:0] $end
$var wire 16 +" outMADDR [15:0] $end
$var reg 16 ," Reg [15:0] $end
$var reg 16 -" Reg_next [15:0] $end
$upscope $end
$upscope $end
$scope begin Gen_Modules[4] $end
$scope module register_inst $end
$var wire 1 ) CLK $end
$var wire 1 ." INCb $end
$var wire 1 /" LDb_ALU $end
$var wire 1 0" LDb_M $end
$var wire 1 1" LDb_P $end
$var wire 1 2" OEb_A $end
$var wire 1 3" OEb_B $end
$var wire 1 4" OEb_M $end
$var wire 1 5" OEb_MADDR $end
$var wire 1 1 RSTb $end
$var wire 16 6" inALU [15:0] $end
$var wire 16 7" inM [15:0] $end
$var wire 16 8" inP [15:0] $end
$var wire 16 9" outA [15:0] $end
$var wire 16 :" outB [15:0] $end
$var wire 16 ;" outM [15:0] $end
$var wire 16 <" outMADDR [15:0] $end
$var reg 16 =" Reg [15:0] $end
$var reg 16 >" Reg_next [15:0] $end
$upscope $end
$upscope $end
$scope begin Gen_Modules[5] $end
$scope module register_inst $end
$var wire 1 ) CLK $end
$var wire 1 ?" INCb $end
$var wire 1 @" LDb_ALU $end
$var wire 1 A" LDb_M $end
$var wire 1 B" LDb_P $end
$var wire 1 C" OEb_A $end
$var wire 1 D" OEb_B $end
$var wire 1 E" OEb_M $end
$var wire 1 F" OEb_MADDR $end
$var wire 1 1 RSTb $end
$var wire 16 G" inALU [15:0] $end
$var wire 16 H" inM [15:0] $end
$var wire 16 I" inP [15:0] $end
$var wire 16 J" outA [15:0] $end
$var wire 16 K" outB [15:0] $end
$var wire 16 L" outM [15:0] $end
$var wire 16 M" outMADDR [15:0] $end
$var reg 16 N" Reg [15:0] $end
$var reg 16 O" Reg_next [15:0] $end
$upscope $end
$upscope $end
$scope begin Gen_Modules[6] $end
$scope module register_inst $end
$var wire 1 ) CLK $end
$var wire 1 P" INCb $end
$var wire 1 Q" LDb_ALU $end
$var wire 1 R" LDb_M $end
$var wire 1 S" LDb_P $end
$var wire 1 T" OEb_A $end
$var wire 1 U" OEb_B $end
$var wire 1 V" OEb_M $end
$var wire 1 W" OEb_MADDR $end
$var wire 1 1 RSTb $end
$var wire 16 X" inALU [15:0] $end
$var wire 16 Y" inM [15:0] $end
$var wire 16 Z" inP [15:0] $end
$var wire 16 [" outA [15:0] $end
$var wire 16 \" outB [15:0] $end
$var wire 16 ]" outM [15:0] $end
$var wire 16 ^" outMADDR [15:0] $end
$var reg 16 _" Reg [15:0] $end
$var reg 16 `" Reg_next [15:0] $end
$upscope $end
$upscope $end
$scope begin Gen_Modules[7] $end
$scope module register_inst $end
$var wire 1 ) CLK $end
$var wire 1 a" INCb $end
$var wire 1 b" LDb_ALU $end
$var wire 1 c" LDb_M $end
$var wire 1 d" LDb_P $end
$var wire 1 e" OEb_A $end
$var wire 1 f" OEb_B $end
$var wire 1 g" OEb_M $end
$var wire 1 h" OEb_MADDR $end
$var wire 1 1 RSTb $end
$var wire 16 i" inALU [15:0] $end
$var wire 16 j" inM [15:0] $end
$var wire 16 k" inP [15:0] $end
$var wire 16 l" outA [15:0] $end
$var wire 16 m" outB [15:0] $end
$var wire 16 n" outM [15:0] $end
$var wire 16 o" outMADDR [15:0] $end
$var reg 16 p" Reg [15:0] $end
$var reg 16 q" Reg_next [15:0] $end
$upscope $end
$upscope $end
$upscope $end
$upscope $end
$enddefinitions $end
#0
$dumpvars
bx q"
bx p"
bx o"
bz n"
bx m"
bx l"
b0 k"
b0 j"
b0 i"
1h"
1g"
1f"
1e"
1d"
1c"
1b"
1a"
bx `"
bx _"
bx ^"
bz ]"
bx \"
bx ["
b0 Z"
b0 Y"
b0 X"
1W"
1V"
1U"
1T"
1S"
1R"
1Q"
1P"
bx O"
bx N"
bx M"
bz L"
bx K"
bx J"
b0 I"
b0 H"
b0 G"
1F"
1E"
1D"
1C"
1B"
1A"
1@"
1?"
bx >"
bx ="
bx <"
bz ;"
bx :"
bx 9"
b0 8"
b0 7"
b0 6"
15"
14"
13"
12"
11"
10"
1/"
1."
bx -"
bx ,"
bx +"
bz *"
bx )"
bx ("
b0 '"
b0 &"
b0 %"
1$"
1#"
1""
1!"
1~
1}
1|
1{
bx z
bx y
bx x
bz w
bx v
bx u
b0 t
b0 s
b0 r
1q
1p
1o
1n
1m
1l
1k
1j
bx i
bx h
bx g
bz f
bx e
bx d
b0 c
b0 b
b0 a
1`
1_
1^
1]
1\
1[
1Z
1Y
bx X
bx W
bx V
bz U
bx T
bx S
b0 R
b0 Q
b0 P
0O
1N
0M
0L
1K
1J
1I
1H
bz G
bx F
b0 E
b0 D
b0 C
bx B
bx A
b11111110 @
b0 ?
b11111110 >
b0 =
b11111111 <
b11111111 ;
b11111111 :
b11111111 9
b11111110 8
b0 7
b11111110 6
b0 5
b0 4
b0 3
b0 2
01
b0 0
1/
b0 .
b11111111 -
b11111111 ,
b11111111 +
b11111111 *
0)
b0 (
b0 '
1&
1%
bz $
bx #
bx "
bx !
$end
#10000
b0 X
b0 !
b0 A
b0 S
b0 d
b0 u
b0 ("
b0 9"
b0 J"
b0 ["
b0 l"
b0 "
b0 B
b0 T
b0 e
b0 v
b0 )"
b0 :"
b0 K"
b0 \"
b0 m"
b0 #
b0 F
b0 V
b0 g
b0 x
b0 +"
b0 <"
b0 M"
b0 ^"
b0 o"
b0 i
b0 z
b0 -"
b0 >"
b0 O"
b0 `"
b0 q"
b0 W
b0 h
b0 y
b0 ,"
b0 ="
b0 N"
b0 _"
b0 p"
1)
#20000
0)
#30000
1)
#40000
0)
#50000
1)
#60000
0)
#70000
1)
#80000
0)
#90000
1)
#100000
0)
11
#110000
1)
#120000
0)
#130000
1)
#140000
0)
#150000
1)
#160000
0)
#170000
1)
#180000
0)
#190000
1)
#200000
b11 X
0K
0)
b11111110 -
b11111110 <
b11 4
b11 E
b11 R
b11 c
b11 t
b11 '"
b11 8"
b11 I"
b11 Z"
b11 k"
#210000
b11 !
b11 A
b11 S
b11 d
b11 u
b11 ("
b11 9"
b11 J"
b11 ["
b11 l"
b11 "
b11 B
b11 T
b11 e
b11 v
b11 )"
b11 :"
b11 K"
b11 \"
b11 m"
b11 #
b11 F
b11 V
b11 g
b11 x
b11 +"
b11 <"
b11 M"
b11 ^"
b11 o"
b11 W
1)
#220000
b10 i
1K
0\
b11 X
0)
b11111101 -
b11111101 <
b10 4
b10 E
b10 R
b10 c
b10 t
b10 '"
b10 8"
b10 I"
b10 Z"
b10 k"
#230000
b10 h
1)
#240000
b10 "
b10 B
b10 T
b10 e
b10 v
b10 )"
b10 :"
b10 K"
b10 \"
b10 m"
1M
0^
b11111101 8
1\
0)
b1 (
b1 7
b11111111 -
b11111111 <
#250000
1)
#260000
b100 X
0H
0)
b11111110 9
b11111110 *
#270000
b101 X
b100 !
b100 A
b100 S
b100 d
b100 u
b100 ("
b100 9"
b100 J"
b100 ["
b100 l"
b100 #
b100 F
b100 V
b100 g
b100 x
b100 +"
b100 <"
b100 M"
b100 ^"
b100 o"
b100 W
1)
#280000
0)
#290000
b110 X
b101 !
b101 A
b101 S
b101 d
b101 u
b101 ("
b101 9"
b101 J"
b101 ["
b101 l"
b101 #
b101 F
b101 V
b101 g
b101 x
b101 +"
b101 <"
b101 M"
b101 ^"
b101 o"
b101 W
1)
#300000
0)
#310000
b111 X
b110 !
b110 A
b110 S
b110 d
b110 u
b110 ("
b110 9"
b110 J"
b110 ["
b110 l"
b110 #
b110 F
b110 V
b110 g
b110 x
b110 +"
b110 <"
b110 M"
b110 ^"
b110 o"
b110 W
1)
#320000
0)
#330000
b1000 X
b111 !
b111 A
b111 S
b111 d
b111 u
b111 ("
b111 9"
b111 J"
b111 ["
b111 l"
b111 #
b111 F
b111 V
b111 g
b111 x
b111 +"
b111 <"
b111 M"
b111 ^"
b111 o"
b111 W
1)
#340000
0)
#350000
b1001 X
b1000 !
b1000 A
b1000 S
b1000 d
b1000 u
b1000 ("
b1000 9"
b1000 J"
b1000 ["
b1000 l"
b1000 #
b1000 F
b1000 V
b1000 g
b1000 x
b1000 +"
b1000 <"
b1000 M"
b1000 ^"
b1000 o"
b1000 W
1)
#360000
0)
#370000
b1010 X
b1001 !
b1001 A
b1001 S
b1001 d
b1001 u
b1001 ("
b1001 9"
b1001 J"
b1001 ["
b1001 l"
b1001 #
b1001 F
b1001 V
b1001 g
b1001 x
b1001 +"
b1001 <"
b1001 M"
b1001 ^"
b1001 o"
b1001 W
1)
#380000
0)
#390000
b1011 X
b1010 !
b1010 A
b1010 S
b1010 d
b1010 u
b1010 ("
b1010 9"
b1010 J"
b1010 ["
b1010 l"
b1010 #
b1010 F
b1010 V
b1010 g
b1010 x
b1010 +"
b1010 <"
b1010 M"
b1010 ^"
b1010 o"
b1010 W
1)
#400000
0)
#410000
b1100 X
b1011 !
b1011 A
b1011 S
b1011 d
b1011 u
b1011 ("
b1011 9"
b1011 J"
b1011 ["
b1011 l"
b1011 #
b1011 F
b1011 V
b1011 g
b1011 x
b1011 +"
b1011 <"
b1011 M"
b1011 ^"
b1011 o"
b1011 W
1)
#420000
0)
#430000
b1101 X
b1100 !
b1100 A
b1100 S
b1100 d
b1100 u
b1100 ("
b1100 9"
b1100 J"
b1100 ["
b1100 l"
b1100 #
b1100 F
b1100 V
b1100 g
b1100 x
b1100 +"
b1100 <"
b1100 M"
b1100 ^"
b1100 o"
b1100 W
1)
#440000
0)
#450000
b1110 X
b1101 !
b1101 A
b1101 S
b1101 d
b1101 u
b1101 ("
b1101 9"
b1101 J"
b1101 ["
b1101 l"
b1101 #
b1101 F
b1101 V
b1101 g
b1101 x
b1101 +"
b1101 <"
b1101 M"
b1101 ^"
b1101 o"
b1101 W
1)
#460000
0)
#470000
b1111 X
b1110 !
b1110 A
b1110 S
b1110 d
b1110 u
b1110 ("
b1110 9"
b1110 J"
b1110 ["
b1110 l"
b1110 #
b1110 F
b1110 V
b1110 g
b1110 x
b1110 +"
b1110 <"
b1110 M"
b1110 ^"
b1110 o"
b1110 W
1)
#480000
0)
#490000
b10000 X
b1111 !
b1111 A
b1111 S
b1111 d
b1111 u
b1111 ("
b1111 9"
b1111 J"
b1111 ["
b1111 l"
b1111 #
b1111 F
b1111 V
b1111 g
b1111 x
b1111 +"
b1111 <"
b1111 M"
b1111 ^"
b1111 o"
b1111 W
1)
#500000
0)
#510000
b10001 X
b10000 !
b10000 A
b10000 S
b10000 d
b10000 u
b10000 ("
b10000 9"
b10000 J"
b10000 ["
b10000 l"
b10000 #
b10000 F
b10000 V
b10000 g
b10000 x
b10000 +"
b10000 <"
b10000 M"
b10000 ^"
b10000 o"
b10000 W
1)
#520000
0)
#530000
b10010 X
b10001 !
b10001 A
b10001 S
b10001 d
b10001 u
b10001 ("
b10001 9"
b10001 J"
b10001 ["
b10001 l"
b10001 #
b10001 F
b10001 V
b10001 g
b10001 x
b10001 +"
b10001 <"
b10001 M"
b10001 ^"
b10001 o"
b10001 W
1)
#540000
0)
#550000
b10011 X
b10010 !
b10010 A
b10010 S
b10010 d
b10010 u
b10010 ("
b10010 9"
b10010 J"
b10010 ["
b10010 l"
b10010 #
b10010 F
b10010 V
b10010 g
b10010 x
b10010 +"
b10010 <"
b10010 M"
b10010 ^"
b10010 o"
b10010 W
1)
#560000
0)
#570000
b10100 X
b10011 !
b10011 A
b10011 S
b10011 d
b10011 u
b10011 ("
b10011 9"
b10011 J"
b10011 ["
b10011 l"
b10011 #
b10011 F
b10011 V
b10011 g
b10011 x
b10011 +"
b10011 <"
b10011 M"
b10011 ^"
b10011 o"
b10011 W
1)
#580000
0)
#590000
b10101 X
b10100 !
b10100 A
b10100 S
b10100 d
b10100 u
b10100 ("
b10100 9"
b10100 J"
b10100 ["
b10100 l"
b10100 #
b10100 F
b10100 V
b10100 g
b10100 x
b10100 +"
b10100 <"
b10100 M"
b10100 ^"
b10100 o"
b10100 W
1)
#600000
0)
#610000
b10110 X
b10101 !
b10101 A
b10101 S
b10101 d
b10101 u
b10101 ("
b10101 9"
b10101 J"
b10101 ["
b10101 l"
b10101 #
b10101 F
b10101 V
b10101 g
b10101 x
b10101 +"
b10101 <"
b10101 M"
b10101 ^"
b10101 o"
b10101 W
1)
#620000
0)
#630000
b10111 X
b10110 !
b10110 A
b10110 S
b10110 d
b10110 u
b10110 ("
b10110 9"
b10110 J"
b10110 ["
b10110 l"
b10110 #
b10110 F
b10110 V
b10110 g
b10110 x
b10110 +"
b10110 <"
b10110 M"
b10110 ^"
b10110 o"
b10110 W
1)
#640000
0)
#650000
b11000 X
b10111 !
b10111 A
b10111 S
b10111 d
b10111 u
b10111 ("
b10111 9"
b10111 J"
b10111 ["
b10111 l"
b10111 #
b10111 F
b10111 V
b10111 g
b10111 x
b10111 +"
b10111 <"
b10111 M"
b10111 ^"
b10111 o"
b10111 W
1)
#660000
0)
#670000
b11001 X
b11000 !
b11000 A
b11000 S
b11000 d
b11000 u
b11000 ("
b11000 9"
b11000 J"
b11000 ["
b11000 l"
b11000 #
b11000 F
b11000 V
b11000 g
b11000 x
b11000 +"
b11000 <"
b11000 M"
b11000 ^"
b11000 o"
b11000 W
1)
#680000
0)
#690000
b11010 X
b11001 !
b11001 A
b11001 S
b11001 d
b11001 u
b11001 ("
b11001 9"
b11001 J"
b11001 ["
b11001 l"
b11001 #
b11001 F
b11001 V
b11001 g
b11001 x
b11001 +"
b11001 <"
b11001 M"
b11001 ^"
b11001 o"
b11001 W
1)
#700000
0)
#710000
b11011 X
b11010 !
b11010 A
b11010 S
b11010 d
b11010 u
b11010 ("
b11010 9"
b11010 J"
b11010 ["
b11010 l"
b11010 #
b11010 F
b11010 V
b11010 g
b11010 x
b11010 +"
b11010 <"
b11010 M"
b11010 ^"
b11010 o"
b11010 W
1)
#720000
0)
#730000
b11100 X
b11011 !
b11011 A
b11011 S
b11011 d
b11011 u
b11011 ("
b11011 9"
b11011 J"
b11011 ["
b11011 l"
b11011 #
b11011 F
b11011 V
b11011 g
b11011 x
b11011 +"
b11011 <"
b11011 M"
b11011 ^"
b11011 o"
b11011 W
1)
#740000
0)
#750000
b11101 X
b11100 !
b11100 A
b11100 S
b11100 d
b11100 u
b11100 ("
b11100 9"
b11100 J"
b11100 ["
b11100 l"
b11100 #
b11100 F
b11100 V
b11100 g
b11100 x
b11100 +"
b11100 <"
b11100 M"
b11100 ^"
b11100 o"
b11100 W
1)
#760000
0)
#770000
b11110 X
b11101 !
b11101 A
b11101 S
b11101 d
b11101 u
b11101 ("
b11101 9"
b11101 J"
b11101 ["
b11101 l"
b11101 #
b11101 F
b11101 V
b11101 g
b11101 x
b11101 +"
b11101 <"
b11101 M"
b11101 ^"
b11101 o"
b11101 W
1)
#780000
0)
#790000
b11111 X
b11110 !
b11110 A
b11110 S
b11110 d
b11110 u
b11110 ("
b11110 9"
b11110 J"
b11110 ["
b11110 l"
b11110 #
b11110 F
b11110 V
b11110 g
b11110 x
b11110 +"
b11110 <"
b11110 M"
b11110 ^"
b11110 o"
b11110 W
1)
#800000
0)
#810000
b100000 X
b11111 !
b11111 A
b11111 S
b11111 d
b11111 u
b11111 ("
b11111 9"
b11111 J"
b11111 ["
b11111 l"
b11111 #
b11111 F
b11111 V
b11111 g
b11111 x
b11111 +"
b11111 <"
b11111 M"
b11111 ^"
b11111 o"
b11111 W
1)
#820000
0)
#830000
b100001 X
b100000 !
b100000 A
b100000 S
b100000 d
b100000 u
b100000 ("
b100000 9"
b100000 J"
b100000 ["
b100000 l"
b100000 #
b100000 F
b100000 V
b100000 g
b100000 x
b100000 +"
b100000 <"
b100000 M"
b100000 ^"
b100000 o"
b100000 W
1)
#840000
0)
#850000
b100010 X
b100001 !
b100001 A
b100001 S
b100001 d
b100001 u
b100001 ("
b100001 9"
b100001 J"
b100001 ["
b100001 l"
b100001 #
b100001 F
b100001 V
b100001 g
b100001 x
b100001 +"
b100001 <"
b100001 M"
b100001 ^"
b100001 o"
b100001 W
1)
#860000
0)
#870000
b100011 X
b100010 !
b100010 A
b100010 S
b100010 d
b100010 u
b100010 ("
b100010 9"
b100010 J"
b100010 ["
b100010 l"
b100010 #
b100010 F
b100010 V
b100010 g
b100010 x
b100010 +"
b100010 <"
b100010 M"
b100010 ^"
b100010 o"
b100010 W
1)
#880000
0)
#890000
b100100 X
b100011 !
b100011 A
b100011 S
b100011 d
b100011 u
b100011 ("
b100011 9"
b100011 J"
b100011 ["
b100011 l"
b100011 #
b100011 F
b100011 V
b100011 g
b100011 x
b100011 +"
b100011 <"
b100011 M"
b100011 ^"
b100011 o"
b100011 W
1)
#900000
0)
#910000
b100101 X
b100100 !
b100100 A
b100100 S
b100100 d
b100100 u
b100100 ("
b100100 9"
b100100 J"
b100100 ["
b100100 l"
b100100 #
b100100 F
b100100 V
b100100 g
b100100 x
b100100 +"
b100100 <"
b100100 M"
b100100 ^"
b100100 o"
b100100 W
1)
#920000
0)
#930000
b100110 X
b100101 !
b100101 A
b100101 S
b100101 d
b100101 u
b100101 ("
b100101 9"
b100101 J"
b100101 ["
b100101 l"
b100101 #
b100101 F
b100101 V
b100101 g
b100101 x
b100101 +"
b100101 <"
b100101 M"
b100101 ^"
b100101 o"
b100101 W
1)
#940000
0)
#950000
b100111 X
b100110 !
b100110 A
b100110 S
b100110 d
b100110 u
b100110 ("
b100110 9"
b100110 J"
b100110 ["
b100110 l"
b100110 #
b100110 F
b100110 V
b100110 g
b100110 x
b100110 +"
b100110 <"
b100110 M"
b100110 ^"
b100110 o"
b100110 W
1)
#960000
0)
#970000
b101000 X
b100111 !
b100111 A
b100111 S
b100111 d
b100111 u
b100111 ("
b100111 9"
b100111 J"
b100111 ["
b100111 l"
b100111 #
b100111 F
b100111 V
b100111 g
b100111 x
b100111 +"
b100111 <"
b100111 M"
b100111 ^"
b100111 o"
b100111 W
1)
#980000
0)
#990000
b101001 X
b101000 !
b101000 A
b101000 S
b101000 d
b101000 u
b101000 ("
b101000 9"
b101000 J"
b101000 ["
b101000 l"
b101000 #
b101000 F
b101000 V
b101000 g
b101000 x
b101000 +"
b101000 <"
b101000 M"
b101000 ^"
b101000 o"
b101000 W
1)
#1000000
0)
#1010000
b101010 X
b101001 !
b101001 A
b101001 S
b101001 d
b101001 u
b101001 ("
b101001 9"
b101001 J"
b101001 ["
b101001 l"
b101001 #
b101001 F
b101001 V
b101001 g
b101001 x
b101001 +"
b101001 <"
b101001 M"
b101001 ^"
b101001 o"
b101001 W
1)
#1020000
0)
